jira_cli_mcp/__init__.py
jira_cli_mcp/server.py
jira_cli_mcp-0.1.0.dist-info/METADATA
jira_cli_mcp-0.1.0.dist-info/WHEEL
jira_cli_mcp-0.1.0.dist-info/entry_points.txt
jira_cli_mcp-0.1.0.dist-info/RECORD
