Metadata-Version: 2.4
Name: jira-cli-mcp
Version: 0.1.0
Summary: Jira CLI as an MCP
Project-URL: Homepage, https://github.com/benomahony/jira_cli_mcp
Project-URL: Bug Tracker, https://github.com/benomahony/jira_cli_mcp/issues
Author-email: Ben O'Mahony <ben@benomahony.com>
License: MIT
Classifier: Development Status :: 4 - Beta
Classifier: Intended Audience :: Developers
Classifier: License :: OSI Approved :: MIT License
Classifier: Programming Language :: Python :: 3
Classifier: Programming Language :: Python :: 3.11
Classifier: Programming Language :: Python :: 3.12
Classifier: Topic :: Software Development :: Libraries :: Python Modules
Requires-Python: >=3.11
Requires-Dist: mcp[cli]>=1.9.3
